llama_index/evaluation/tonic_validate/__init__.py
llama_index/evaluation/tonic_validate/answer_consistency.py
llama_index/evaluation/tonic_validate/answer_consistency_binary.py
llama_index/evaluation/tonic_validate/answer_similarity.py
llama_index/evaluation/tonic_validate/augmentation_accuracy.py
llama_index/evaluation/tonic_validate/augmentation_precision.py
llama_index/evaluation/tonic_validate/retrieval_precision.py
llama_index/evaluation/tonic_validate/tonic_validate_evaluator.py
llama_index_evaluation_tonic_validate-0.5.1.dist-info/METADATA
llama_index_evaluation_tonic_validate-0.5.1.dist-info/WHEEL
llama_index_evaluation_tonic_validate-0.5.1.dist-info/licenses/LICENSE
llama_index_evaluation_tonic_validate-0.5.1.dist-info/RECORD
