Metadata-Version: 2.4
Name: llama-index-evaluation-tonic-validate
Version: 0.5.1
Summary: llama-index evaluation tonic validate integration
Author-email: Your Name <you@example.com>
License-Expression: MIT
License-File: LICENSE
Requires-Python: <4.0,>=3.9
Requires-Dist: aioboto3<13.0.0,>=12.4.0
Requires-Dist: llama-index-core<0.15,>=0.13.0
Requires-Dist: tonic-validate<7,>=6.1.0
